{"type":"FeatureCollection","features":[{"id":"034FWFDERAYNES","type":"Feature","geometry":{"bbox":[-1.440152,52.906523,-1.430563,52.912352],"type":"MultiPolygon","coordinates":[[[[-1.43667,52.908836],[-1.436656,52.908818],[-1.43565,52.90839],[-1.434144,52.906523],[-1.432098,52.906676],[-1.431553,52.907143],[-1.431578,52.907651],[-1.431589,52.908024],[-1.430563,52.910118],[-1.431476,52.910591],[-1.435066,52.912352],[-1.440152,52.910924],[-1.439161,52.910119],[-1.43667,52.908836]]]]},"properties":{"code":"034FWFDERAYNES","name":"River Derwent at Raynesway","type_id":"f","centroid":{"type":"Point","coordinates":[-1.434663,52.909659]},"river_sea":"River Derwent","ea_area_id":"EMD","category_id":"fwa","description":"River Derwent at Raynesway including the Works area","ea_owner_id":"034","quick_dial_code":"306067","parent_area_code":"034WAF409","local_authority_name":"Derby"}}]}